nextguild/__init__.py
nextguild/classes.py
nextguild/client.py
nextguild/embed.py
nextguild/events.py
nextguild-1.2.16.dist-info/LICENSE
nextguild-1.2.16.dist-info/METADATA
nextguild-1.2.16.dist-info/WHEEL
nextguild-1.2.16.dist-info/top_level.txt
nextguild-1.2.16.dist-info/RECORD
