Metadata-Version: 2.1
Name: nextguild
Version: 1.2.16
Summary: Interactions with the Guilded API made simpler
Author-email: Arjun Sharda <sharda.aj17@gmail.com>, Erik Thorsell <contact@erikthorsell.com>
License: MIT License
Project-URL: Homepage, https://github.com/ArjunSharda/nextguild
Project-URL: Bug Tracker, https://github.com/ArjunSharda/nextguild/issues
Classifier: Programming Language :: Python :: 3
Classifier: License :: OSI Approved :: MIT License
Classifier: Operating System :: OS Independent
Requires-Python: >=3.7
License-File: LICENSE
